rvtools/__init__.py
rvtools/corerv.py
rvtools/rvtools.py
rvtools/rvtools_db.py
rvtools/test.py
rvtools/printrv/__init__.py
rvtools/printrv/csv_print.py
rvtools/vinfo/__init__.py
rvtools/vinfo/vinfo.py
rvtools_python-1.0.0.data/scripts/rvtools
test/__init__.py
rvtools_python-1.0.0.dist-info/METADATA
rvtools_python-1.0.0.dist-info/WHEEL
rvtools_python-1.0.0.dist-info/top_level.txt
rvtools_python-1.0.0.dist-info/RECORD
