Metadata-Version: 2.1
Name: rvtools_python
Version: 1.0.0
Summary: Simple app to collect information from vSphere
Home-page: https://github.com/waldirio/rvtools_python/
Author: Waldirio
Author-email: waldirio@gmail.com
Classifier: Programming Language :: Python :: 3
Classifier: License :: OSI Approved :: MIT License
Classifier: Operating System :: OS Independent
Requires-Python: >=3.9
Requires-Dist: altgraph ==0.17.4
Requires-Dist: appnope ==0.1.4
Requires-Dist: astroid ==3.0.3
Requires-Dist: asttokens ==2.4.1
Requires-Dist: backcall ==0.2.0
Requires-Dist: certifi ==2024.2.2
Requires-Dist: chardet ==5.2.0
Requires-Dist: charset-normalizer ==3.3.2
Requires-Dist: decorator ==5.1.1
Requires-Dist: dill ==0.3.8
Requires-Dist: docopt ==0.6.2
Requires-Dist: exceptiongroup ==1.2.0
Requires-Dist: executing ==2.0.1
Requires-Dist: flake8 ==7.0.0
Requires-Dist: gitdb ==4.0.11
Requires-Dist: gitdb2 ==4.0.2
Requires-Dist: GitPython ==3.1.42
Requires-Dist: idna ==3.6
Requires-Dist: importlib-metadata ==7.0.1
Requires-Dist: ipython ==8.18.1
Requires-Dist: ipython-genutils ==0.2.0
Requires-Dist: isort ==5.13.2
Requires-Dist: jedi ==0.19.1
Requires-Dist: lazy-object-proxy ==1.10.0
Requires-Dist: lint ==1.2.1
Requires-Dist: macholib ==1.16.3
Requires-Dist: matplotlib-inline ==0.1.6
Requires-Dist: mccabe ==0.7.0
Requires-Dist: packaging ==23.2
Requires-Dist: parso ==0.8.3
Requires-Dist: pexpect ==4.9.0
Requires-Dist: pickleshare ==0.7.5
Requires-Dist: platformdirs ==4.2.0
Requires-Dist: prompt-toolkit ==3.0.43
Requires-Dist: ptyprocess ==0.7.0
Requires-Dist: pure-eval ==0.2.2
Requires-Dist: pycodestyle ==2.11.1
Requires-Dist: pyflakes ==3.2.0
Requires-Dist: Pygments ==2.17.2
Requires-Dist: pyinstaller ==6.4.0
Requires-Dist: pyinstaller-hooks-contrib ==2024.1
Requires-Dist: pylint ==3.0.3
Requires-Dist: pytoolconfig ==1.3.1
Requires-Dist: pyvim ==3.0.3
Requires-Dist: pyvmomi ==8.0.2.0.1
Requires-Dist: requests ==2.31.0
Requires-Dist: rope ==1.12.0
Requires-Dist: simplegeneric ==0.8.1
Requires-Dist: six ==1.16.0
Requires-Dist: smmap ==5.0.1
Requires-Dist: smmap2 ==3.0.1
Requires-Dist: stack-data ==0.6.3
Requires-Dist: toml ==0.10.2
Requires-Dist: tomli ==2.0.1
Requires-Dist: tomlkit ==0.12.3
Requires-Dist: traitlets ==5.14.1
Requires-Dist: typing-extensions ==4.9.0
Requires-Dist: urllib3 ==2.2.1
Requires-Dist: wcwidth ==0.2.13
Requires-Dist: wrapt ==1.16.0
Requires-Dist: zipp ==3.17.0
